CONSTANTS.py
filament_augmentation/__init__.py
filament_augmentation/augment/__init__.py
filament_augmentation/augment/augmentation.py
filament_augmentation/generator/__init__.py
filament_augmentation/generator/filament_dataset.py
filament_augmentation/generator/filament_generator.py
filament_augmentation/loader/__init__.py
filament_augmentation/loader/filament_dataloader.py
filament_augmentation/metadata/__init__.py
filament_augmentation/metadata/filament_metadata.py
filament_augmentation/transforms/__init__.py
filament_augmentation/transforms/heliographic.py
filament_augmentation/transforms/mercator.py
filament_augmentation/transforms/transformation.py
filament_augmentation/utils/__init__.py
filament_augmentation/utils/file_utilities.py
filament_augmentation/utils/image_utils.py
filament_augmentation/utils/timestamp_utilites.py
augmentation_engine-0.1.2.dist-info/LICENSE
augmentation_engine-0.1.2.dist-info/METADATA
augmentation_engine-0.1.2.dist-info/WHEEL
augmentation_engine-0.1.2.dist-info/top_level.txt
augmentation_engine-0.1.2.dist-info/RECORD
