Metadata-Version: 2.1
Name: augmentation-engine
Version: 0.1.2
Summary: Solar Filaments data augmentation demo package
Home-page: https://bitbucket.org/gsudmlab/augmentation_engine/src/master/
Author: Shreejaa Talla
Author-email: shreejaa.talla@gmail.com
License: UNKNOWN
Project-URL: Source, https://bitbucket.org/gsudmlab/augmentation_engine/src/master/
Platform: UNKNOWN
Classifier: Programming Language :: Python :: 3
Classifier: Operating System :: OS Independent
Classifier: License :: OSI Approved :: MIT License
Requires-Dist: sortedcontainers
Requires-Dist: opencv-python
Requires-Dist: torchvision
Requires-Dist: pillow
Requires-Dist: pycocotools
